README.rst
setup.py
cloudflare_flask_ipban/__init__.py
cloudflare_flask_ipban/abuse_ipdb.py
cloudflare_flask_ipban/get_lock.py
cloudflare_flask_ipban/ip_ban.py
cloudflare_flask_ipban/ip_record.py
cloudflare_flask_ipban/test.py
cloudflare_flask_ipban/test_persistence.py
cloudflare_flask_ipban.egg-info/PKG-INFO
cloudflare_flask_ipban.egg-info/SOURCES.txt
cloudflare_flask_ipban.egg-info/dependency_links.txt
cloudflare_flask_ipban.egg-info/requires.txt
cloudflare_flask_ipban.egg-info/top_level.txt