Metadata-Version: 2.1
Name: cloudflare-flask-ipban
Version: 1.1.7
Summary: URL spam security for Flask, modified for cloudflare.
Home-page: https://github.com/mte0/cloudflare-flask-ipban
Author: mte & Andrew Rowe
License: Apache Software License
Download-URL: https://github.com/mte0/cloudflare-flask-ipban/archive/1.1.7.tar.gz
Keywords: flask security spam url ban cloudflare
Platform: UNKNOWN
Classifier: Development Status :: 5 - Production/Stable
Classifier: Intended Audience :: Developers
Classifier: Topic :: Software Development :: Libraries :: Python Modules
Classifier: License :: OSI Approved :: Apache Software License
Classifier: Programming Language :: Python
Classifier: Programming Language :: Python :: 3
Classifier: Programming Language :: Python :: 3.6
Classifier: Programming Language :: Python :: 3.7
Classifier: Programming Language :: Python :: 3.8
Classifier: Operating System :: POSIX
Classifier: Operating System :: MacOS
Classifier: Operating System :: Unix
Classifier: Operating System :: Microsoft :: Windows
Classifier: Framework :: Flask
